tian_repository/__init__.py
tian_repository/base/__init__.py
tian_repository/base/run.sh
tian_repository/base/src/common.py
tian_repository/base/src/sql_builder.py
tian_repository/base/tests/test_sql_builder.py
tian_repository/bigquery/__init__.py
tian_repository/bigquery/migration.py
tian_repository/file_storage/__init__.py
tian_repository/file_storage/drive.py
tian_repository/file_storage/examples.py
tian_repository/file_storage/repository.py
tian_repository/file_storage/test.py
tian_repository/memory/__init__.py
tian_repository/memory/repository.py
tian_repository/mock/__init__.py
tian_repository/mock/pyproject.toml
tian_repository/mock/repository.py
tian_repository/mongo/__init__.py
tian_repository/mongo/common.py
tian_repository/mongo/repository.py
tian_repository/postgres/__init__.py
tian_repository/postgres/pyproject.toml
tian_repository/postgres/src/repository.py
tian_repository/redis/__init__.py
tian_repository/redis/pyproject.toml
tian_repository/redis/repository.py
tian_repository/sheet/__init__.py
tian_repository/sheet/examples.py
tian_repository/sheet/repository.py
tian_repository/sqlite/__init__.py
tian_repository-0.1.0.dist-info/LICENSE
tian_repository-0.1.0.dist-info/METADATA
tian_repository-0.1.0.dist-info/WHEEL
tian_repository-0.1.0.dist-info/RECORD
