Metadata-Version: 2.1
Name: tian_repository
Version: 0.1.0
Summary: python.thienhang.com
Author: open-thienhang-com
Requires-Python: >=3.11,<4.0
Classifier: Programming Language :: Python :: 3
Classifier: Programming Language :: Python :: 3.11
Classifier: Programming Language :: Python :: 3.12
Classifier: Programming Language :: Python :: 3.13
